[
  {
    "model": "student.school",
    "fields": {
      "id": 6001,
      "name": "School 1",
      "address": "123 Green Valley Road, Dhaka",
      "email": "contact@greenvalley.edu.bd",
      "contact_number": "01711123456",
      "website": "http://greenvalley.edu.bd",
      "logo": "school_logos/green_valley.png"
    }
  },
  {
    "model": "student.school",
    "fields": {
      "id": 6002,
      "name": "School 2",
      "address": "45 Ocean Drive, Chittagong",
      "email": "info@blueocean.edu.bd",
      "contact_number": "01888876543",
      "website": "http://blueocean.edu.bd",
      "logo": "school_logos/blue_ocean.png"
    }
  },
  {
    "model": "student.school",
    "fields": {
      "id": 6003,
      "name": "School 3",
      "address": "56 Golden Street, Sylhet",
      "email": "admin@goldenfuture.edu.bd",
      "contact_number": "01999987654",
      "website": "http://goldenfuture.edu.bd",
      "logo": "school_logos/golden_future.png"
    }
  }
]
